biopt/__init__.py
biopt/core.py
biopt-0.0.1.dist-info/licenses/AUTHORS.md
biopt-0.0.1.dist-info/METADATA
biopt-0.0.1.dist-info/WHEEL
biopt-0.0.1.dist-info/top_level.txt
biopt-0.0.1.dist-info/RECORD
