Metadata-Version: 2.4
Name: BiOpt
Version: 0.0.1
Summary: NREL's BiOpt model
Author-email: Guilherme Castelao <gpimenta@nrel.gov>
Maintainer-email: Guilherme Castelao <gpimenta@nrel.gov>
License-Expression: MIT
Project-URL: homepage, https://github.com/NREL/BiOpt
Project-URL: documentation, https://github.com/NREL/BiOpt
Project-URL: repository, https://github.com/NREL/BiOpt
Keywords: NREL,best practices
Classifier: Development Status :: 2 - Pre-Alpha
Classifier: Intended Audience :: Science/Research
Classifier: Natural Language :: English
Classifier: Operating System :: OS Independent
Classifier: Programming Language :: Python :: 3
Classifier: Programming Language :: Python :: 3.11
Classifier: Programming Language :: Python :: 3.12
Classifier: Programming Language :: Python :: 3.13
Classifier: Topic :: Software Development :: Libraries :: Application Frameworks
Requires-Python: >=3.11
License-File: AUTHORS.md
Provides-Extra: dev
Requires-Dist: ipython>=8.29; extra == "dev"
Requires-Dist: ruff>=0.7; extra == "dev"
Requires-Dist: uv>=0.7; extra == "dev"
Provides-Extra: doc
Requires-Dist: make>=0.1; extra == "doc"
Requires-Dist: ghp-import>=2.1; extra == "doc"
Requires-Dist: numpydoc>=1.6; extra == "doc"
Requires-Dist: pandoc>=2.3; extra == "doc"
Requires-Dist: sphinx>=7.2; extra == "doc"
Requires-Dist: sphinx-click>=5.1; extra == "doc"
Requires-Dist: sphinx-tabs>=3.4; extra == "doc"
Requires-Dist: sphinx-copybutton>=0.5; extra == "doc"
Requires-Dist: pydata-sphinx-theme>=0.15; extra == "doc"
Provides-Extra: test
Requires-Dist: pytest>=8.0.0; extra == "test"
Requires-Dist: pytest-cov>=5.0.0; extra == "test"
Requires-Dist: pytest-xdist>=3.5.0; extra == "test"
Dynamic: license-file
